maestro/__init__.py
maestro/cli/__init__.py
maestro/cli/cli.py
maestro/client/__init__.py
maestro/client/client.py
maestro/client/watch.py
maestro/dsl/__init__.py
maestro/dsl/jobs.py
maestro/dsl/workflow.py
maestro_sdk-0.1.4.dist-info/licenses/LICENSE
maestro_sdk-0.1.4.dist-info/METADATA
maestro_sdk-0.1.4.dist-info/WHEEL
maestro_sdk-0.1.4.dist-info/entry_points.txt
maestro_sdk-0.1.4.dist-info/top_level.txt
maestro_sdk-0.1.4.dist-info/RECORD
