Metadata-Version: 2.4
Name: maestro-sdk
Version: 0.1.4
Summary: Python SDK client for Netflix Maestro workflow orchestrator
Author-email: Jun He <jun-he@users.noreply.github.com>
License-Expression: Apache-2.0
Keywords: maestro,workflow,orchestration,SDK,DSL
Classifier: Development Status :: 3 - Alpha
Classifier: Intended Audience :: Developers
Classifier: Programming Language :: Python :: 3
Classifier: Programming Language :: Python :: 3.10
Classifier: Programming Language :: Python :: 3.11
Classifier: Programming Language :: Python :: 3.12
Classifier: Programming Language :: Python :: 3.13
Classifier: Typing :: Typed
Requires-Python: >=3.10
License-File: LICENSE
Requires-Dist: pyyaml>=6.0
Provides-Extra: dev
Requires-Dist: pytest>=7.0; extra == "dev"
Requires-Dist: mypy>=1.0; extra == "dev"
Requires-Dist: types-PyYAML>=6.0; extra == "dev"
Dynamic: license-file
